emailspoofergui/__init__.py
emailspoofergui/emailspoofergui.py
emailspoofergui/data/config.json
emailspoofergui-3.4.dist-info/LICENSE
emailspoofergui-3.4.dist-info/METADATA
emailspoofergui-3.4.dist-info/WHEEL
emailspoofergui-3.4.dist-info/entry_points.txt
emailspoofergui-3.4.dist-info/top_level.txt
emailspoofergui-3.4.dist-info/RECORD
