Metadata-Version: 2.1
Name: emailspoofergui
Version: 3.4
Summary: A graphical email spoofing tool
Home-page: https://github.com/IMApurbo/emailspoofergui
Author: AKM Korishee Apurbo
Author-email: bandinvisible8@gmail.com
License: MIT
Classifier: License :: OSI Approved :: MIT License
Classifier: Programming Language :: Python :: 3
Classifier: Programming Language :: Python :: 3.6
Classifier: Programming Language :: Python :: 3.7
Classifier: Programming Language :: Python :: 3.8
Classifier: Programming Language :: Python :: 3.9
License-File: LICENSE
Requires-Dist: customtkinter
Requires-Dist: CTkMessagebox
